odoo/addons/mrp_workorder_last_worker/README.rst
odoo/addons/mrp_workorder_last_worker/__init__.py
odoo/addons/mrp_workorder_last_worker/__manifest__.py
odoo/addons/mrp_workorder_last_worker/i18n/it.po
odoo/addons/mrp_workorder_last_worker/i18n/mrp_workorder_last_worker.pot
odoo/addons/mrp_workorder_last_worker/models/__init__.py
odoo/addons/mrp_workorder_last_worker/models/mrp_workorder.py
odoo/addons/mrp_workorder_last_worker/readme/CONTRIBUTORS.rst
odoo/addons/mrp_workorder_last_worker/readme/DESCRIPTION.rst
odoo/addons/mrp_workorder_last_worker/static/description/icon.png
odoo/addons/mrp_workorder_last_worker/static/description/index.html
odoo/addons/mrp_workorder_last_worker/tests/__init__.py
odoo/addons/mrp_workorder_last_worker/tests/test_mrp_workorder_last_worker.py
odoo/addons/mrp_workorder_last_worker/views/mrp_workorder_views.xml
odoo_addon_mrp_workorder_last_worker-16.0.1.1.0.dist-info/METADATA
odoo_addon_mrp_workorder_last_worker-16.0.1.1.0.dist-info/WHEEL
odoo_addon_mrp_workorder_last_worker-16.0.1.1.0.dist-info/top_level.txt
odoo_addon_mrp_workorder_last_worker-16.0.1.1.0.dist-info/RECORD
